<?xml version="1.0" encoding="UTF-8"?>
<persistence version="2.1" xmlns="http://xmlns.jcp.org/xml/ns/persistence" xmlns:xsi="http://www.w3.org/2001/XMLSchema-instance" xsi:schemaLocation="http://xmlns.jcp.org/xml/ns/persistence http://xmlns.jcp.org/xml/ns/persistence/persistence_2_1.xsd">
	<persistence-unit name="ubo">
		<class>Model.Candidat</class>
		<class>Model.Enseignant</class>
		<class>Model.Etudiant</class>
		<class>Model.Formation</class>
		<class>Model.Promotion</class>
		<class>Model.PromotionPk</class>
	</persistence-unit>
</persistence>
